README.md
setup.py
Time_Series_DataAnalysis_Tool/__init__.py
Time_Series_DataAnalysis_Tool.egg-info/PKG-INFO
Time_Series_DataAnalysis_Tool.egg-info/SOURCES.txt
Time_Series_DataAnalysis_Tool.egg-info/dependency_links.txt
Time_Series_DataAnalysis_Tool.egg-info/not-zip-safe
Time_Series_DataAnalysis_Tool.egg-info/top_level.txt