Metadata-Version: 2.1
Name: Time_Series_DataAnalysis_Tool
Version: 0.1.9.1
Summary: provides modules to read and perform analysis of a time series data
Home-page: UNKNOWN
Author: Chetan Raj Rupakheti
Author-email: chetanrrk@gmail.com
License: UNKNOWN
Platform: UNKNOWN
Requires-Python: >=3
